<?xml version="1.0"?>
<save_state>
	<input />
	<window />
	<textures />
	<audio />
	<Physics />
	<Fonts />
	<pathfinding />
	<Scene_manager />
	<sceneIntro />
	<sceneMainMenu />
	<scene>
		<player x="1852" y="5592" />
	</scene>
	<scenecombatLHHR />
	<sceneBattle />
	<sceneGrandma />
	<w2_scene />
	<w3_scene />
	<entitymanager />
	<map />
	<guiManager />
	<UIModule />
	<teamManager>
		<playable istimmyplayable="true" isbunnyplayable="true" islrrhplayable="true" />
		<onteam IsTimmyOnTeam="true" IsBunnyOnTeam="true" IsLrrhOnTeam="true" />
	</teamManager>
	<fadeToBlack />
	<renderer>
		<camera x="-892" y="-4974" />
	</renderer>
</save_state>
